amiibo/__init__.py
amiibo/cli.py
amiibo/crypto.py
amiibo/keys.py
amiibo/ntag.py
pyamiibo-0.2.dist-info/DESCRIPTION.rst
pyamiibo-0.2.dist-info/LICENSE.txt
pyamiibo-0.2.dist-info/METADATA
pyamiibo-0.2.dist-info/RECORD
pyamiibo-0.2.dist-info/WHEEL
pyamiibo-0.2.dist-info/entry_points.txt
pyamiibo-0.2.dist-info/metadata.json
pyamiibo-0.2.dist-info/top_level.txt
pyamiibo-0.2.dist-info/zip-safe
