Metadata-Version: 2.0
Name: pyamiibo
Version: 0.2
Summary: PyAmiibo is a library for manipulating Amiibo dumps.
Home-page: https://github.com/tobywf/pyamiibo
Author: Toby Fleming
Author-email: tobywf@users.noreply.github.com
License: GPLv3
Keywords: NXP NTAG NTAG213 NTAG215 NTAG216 Amiibo
Platform: UNKNOWN
Classifier: Development Status :: 4 - Beta
Classifier: Intended Audience :: Developers
Classifier: License :: OSI Approved :: GNU General Public License v3 (GPLv3)
Classifier: Natural Language :: English
Classifier: Programming Language :: Python :: 3 :: Only
Classifier: Topic :: Software Development :: Libraries
Classifier: Operating System :: OS Independent
Requires-Dist: cryptography
